torch_bnn/__init__.py
torch_bnn/bnn/__init__.py
torch_bnn/bnn/base.py
torch_bnn/bnn/linear.py
torch_bnn/bnn/rnn/__init__.py
torch_bnn/bnn/rnn/base.py
torch_bnn/bnn/rnn/basic.py
torch_bnn/bnn/rnn/lstm.py
torch_bnn/py.typed
torch_bnn-0.3.8.dist-info/LICENSE
torch_bnn-0.3.8.dist-info/WHEEL
torch_bnn-0.3.8.dist-info/METADATA
torch_bnn-0.3.8.dist-info/RECORD
